vention/__init__.py
vention/io/__init__.py
vention/io/v1/__init__.py
vention/io/v1/expander_hub_p2p.py
vention/io/v1/expander_hub_pb2.py
vention/io/v1/expander_hub_pb2_grpc.py
vention/io/v1/expander_hub_service_p2p.py
vention/io/v1/expander_hub_service_pb2.py
vention/io/v1/expander_hub_service_pb2_grpc.py
vention/machine_motion/__init__.py
vention/machine_motion/v1/__init__.py
vention/machine_motion/v1/ethercat_address_p2p.py
vention/machine_motion/v1/ethercat_address_pb2.py
vention/machine_motion/v1/ethercat_address_pb2_grpc.py
vention/machine_motion/v1/ethercat_commands_p2p.py
vention/machine_motion/v1/ethercat_commands_pb2.py
vention/machine_motion/v1/ethercat_commands_pb2_grpc.py
vention/machine_motion/v1/ethercat_p2p.py
vention/machine_motion/v1/ethercat_pb2.py
vention/machine_motion/v1/ethercat_pb2_grpc.py
vention/machine_motion/v1/ethercat_service_p2p.py
vention/machine_motion/v1/ethercat_service_pb2.py
vention/machine_motion/v1/ethercat_service_pb2_grpc.py
vention/machine_motion/v1/ethercat_topology_p2p.py
vention/machine_motion/v1/ethercat_topology_pb2.py
vention/machine_motion/v1/ethercat_topology_pb2_grpc.py
vention/machine_motion/v1/generic_response_p2p.py
vention/machine_motion/v1/generic_response_pb2.py
vention/machine_motion/v1/generic_response_pb2_grpc.py
vention/machine_motion/v1/lan_deploy_p2p.py
vention/machine_motion/v1/lan_deploy_pb2.py
vention/machine_motion/v1/lan_deploy_pb2_grpc.py
vention/machine_motion/v1/plugin_p2p.py
vention/machine_motion/v1/plugin_pb2.py
vention/machine_motion/v1/plugin_pb2_grpc.py
vention/machine_motion/v1/service_manager_p2p.py
vention/machine_motion/v1/service_manager_pb2.py
vention/machine_motion/v1/service_manager_pb2_grpc.py
vention/motors/__init__.py
vention/motors/v1/__init__.py
vention/motors/v1/batch_move_p2p.py
vention/motors/v1/batch_move_pb2.py
vention/motors/v1/batch_move_pb2_grpc.py
vention/motors/v1/configuration_p2p.py
vention/motors/v1/configuration_pb2.py
vention/motors/v1/configuration_pb2_grpc.py
vention_firmware_grpc_client-0.1.1.dist-info/METADATA
vention_firmware_grpc_client-0.1.1.dist-info/WHEEL
vention_firmware_grpc_client-0.1.1.dist-info/RECORD
