Metadata-Version: 2.4
Name: vention-firmware-grpc-client
Version: 0.1.1
Summary: A python grpc client for calling vention firmware endpoints
License: Proprietary
Keywords: Vention,grpc,client,vrmcs,firmware
Author: VentionCo
Requires-Python: >=3.10,<4.0
Classifier: License :: Other/Proprietary License
Classifier: Programming Language :: Python :: 3
Classifier: Programming Language :: Python :: 3.10
Classifier: Programming Language :: Python :: 3.11
Classifier: Programming Language :: Python :: 3.12
Classifier: Programming Language :: Python :: 3.13
Classifier: Programming Language :: Python :: 3.14
Requires-Dist: grpcio (>=1.74.0)
Requires-Dist: grpcio-tools (>=1.74.0)
Requires-Dist: protobuf (>=6.31.1,<7.0.0)
Requires-Dist: protobuf-to-pydantic[all] (>=0.3.3.1,<0.4.0.0)
Requires-Dist: pydantic (<2.12)
